temp_venv.py
temp_venv-0.2.1.dist-info/licenses/LICENSE
temp_venv-0.2.1.dist-info/METADATA
temp_venv-0.2.1.dist-info/WHEEL
temp_venv-0.2.1.dist-info/top_level.txt
temp_venv-0.2.1.dist-info/RECORD
