Metadata-Version: 2.4
Name: temp-venv
Version: 0.2.1
Summary: A context manager for temporary Python virtual environments with extensive configuration options.
Author-email: Henrique Pereira <ikkibr@gmail.com>
License: GNU GENERAL PUBLIC LICENSE
Project-URL: Homepage, https://github.com/ikkebr/temp_venv
Project-URL: Issues, https://github.com/ikkebr/temp_venv/issues
Keywords: venv,virtualenv,temporary,context manager,testing,isolation,automation
Classifier: Development Status :: 4 - Beta
Classifier: Intended Audience :: Developers
Classifier: Topic :: Software Development :: Testing
Classifier: Topic :: Software Development :: Libraries :: Python Modules
Classifier: License :: OSI Approved :: GNU General Public License v2 (GPLv2)
Classifier: Programming Language :: Python :: 3
Classifier: Programming Language :: Python :: 3.9
Classifier: Programming Language :: Python :: 3.10
Classifier: Programming Language :: Python :: 3.11
Classifier: Programming Language :: Python :: 3.12
Classifier: Operating System :: OS Independent
Requires-Python: >=3.9
License-File: LICENSE
Requires-Dist: uv
Dynamic: license-file
